{"timestamp": "2026-05-15T00:00:11.002974+00:00", "daily": {"total_trades": 0, "profitable": 0, "win_rate": 0.0, "profit_factor": 0.0, "avg_win": 0.0, "avg_loss": 0.0, "expectancy": 0.0, "sharpe_ratio": 0.0, "max_drawdown": 0.0, "total_pnl": 0.0, "avg_trade": 0.0, "liquidity_skips": 0, "price_skips": 0}}
{"timestamp": "2026-05-15T00:30:19.354086+00:00", "daily": {"total_trades": 0, "profitable": 0, "win_rate": 0.0, "profit_factor": 0.0, "avg_win": 0.0, "avg_loss": 0.0, "expectancy": 0.0, "sharpe_ratio": 0.0, "max_drawdown": 0.0, "total_pnl": 0.0, "avg_trade": 0.0, "liquidity_skips": 0, "price_skips": 0}}
{"timestamp": "2026-05-15T01:00:34.194250+00:00", "daily": {"total_trades": 0, "profitable": 0, "win_rate": 0.0, "profit_factor": 0.0, "avg_win": 0.0, "avg_loss": 0.0, "expectancy": 0.0, "sharpe_ratio": 0.0, "max_drawdown": 0.0, "total_pnl": 0.0, "avg_trade": 0.0, "liquidity_skips": 0, "price_skips": 0}}
{"timestamp": "2026-05-15T02:00:51.658123+00:00", "daily": {"total_trades": 0, "profitable": 0, "win_rate": 0.0, "profit_factor": 0.0, "avg_win": 0.0, "avg_loss": 0.0, "expectancy": 0.0, "sharpe_ratio": 0.0, "max_drawdown": 0.0, "total_pnl": 0.0, "avg_trade": 0.0, "liquidity_skips": 0, "price_skips": 0}}
{"timestamp": "2026-05-15T02:31:03.306734+00:00", "daily": {"total_trades": 0, "profitable": 0, "win_rate": 0.0, "profit_factor": 0.0, "avg_win": 0.0, "avg_loss": 0.0, "expectancy": 0.0, "sharpe_ratio": 0.0, "max_drawdown": 0.0, "total_pnl": 0.0, "avg_trade": 0.0, "liquidity_skips": 0, "price_skips": 0}}
{"timestamp": "2026-05-15T03:00:17.099003+00:00", "daily": {"total_trades": 0, "profitable": 0, "win_rate": 0.0, "profit_factor": 0.0, "avg_win": 0.0, "avg_loss": 0.0, "expectancy": 0.0, "sharpe_ratio": 0.0, "max_drawdown": 0.0, "total_pnl": 0.0, "avg_trade": 0.0, "liquidity_skips": 0, "price_skips": 0}}
{"timestamp": "2026-05-15T03:30:30.577779+00:00", "daily": {"total_trades": 0, "profitable": 0, "win_rate": 0.0, "profit_factor": 0.0, "avg_win": 0.0, "avg_loss": 0.0, "expectancy": 0.0, "sharpe_ratio": 0.0, "max_drawdown": 0.0, "total_pnl": 0.0, "avg_trade": 0.0, "liquidity_skips": 0, "price_skips": 0}}
{"timestamp": "2026-05-15T04:00:41.880826+00:00", "daily": {"total_trades": 0, "profitable": 0, "win_rate": 0.0, "profit_factor": 0.0, "avg_win": 0.0, "avg_loss": 0.0, "expectancy": 0.0, "sharpe_ratio": 0.0, "max_drawdown": 0.0, "total_pnl": 0.0, "avg_trade": 0.0, "liquidity_skips": 0, "price_skips": 0}}
{"timestamp": "2026-05-15T04:30:55.180123+00:00", "daily": {"total_trades": 0, "profitable": 0, "win_rate": 0.0, "profit_factor": 0.0, "avg_win": 0.0, "avg_loss": 0.0, "expectancy": 0.0, "sharpe_ratio": 0.0, "max_drawdown": 0.0, "total_pnl": 0.0, "avg_trade": 0.0, "liquidity_skips": 0, "price_skips": 0}}
{"timestamp": "2026-05-15T05:01:07.287224+00:00", "daily": {"total_trades": 0, "profitable": 0, "win_rate": 0.0, "profit_factor": 0.0, "avg_win": 0.0, "avg_loss": 0.0, "expectancy": 0.0, "sharpe_ratio": 0.0, "max_drawdown": 0.0, "total_pnl": 0.0, "avg_trade": 0.0, "liquidity_skips": 0, "price_skips": 0}}
{"timestamp": "2026-05-15T05:30:19.266436+00:00", "daily": {"total_trades": 0, "profitable": 0, "win_rate": 0.0, "profit_factor": 0.0, "avg_win": 0.0, "avg_loss": 0.0, "expectancy": 0.0, "sharpe_ratio": 0.0, "max_drawdown": 0.0, "total_pnl": 0.0, "avg_trade": 0.0, "liquidity_skips": 0, "price_skips": 0}}
{"timestamp": "2026-05-15T06:00:30.409221+00:00", "daily": {"total_trades": 0, "profitable": 0, "win_rate": 0.0, "profit_factor": 0.0, "avg_win": 0.0, "avg_loss": 0.0, "expectancy": 0.0, "sharpe_ratio": 0.0, "max_drawdown": 0.0, "total_pnl": 0.0, "avg_trade": 0.0, "liquidity_skips": 0, "price_skips": 0}}
{"timestamp": "2026-05-15T06:30:23.325534+00:00", "daily": {"total_trades": 0, "profitable": 0, "win_rate": 0.0, "profit_factor": 0.0, "avg_win": 0.0, "avg_loss": 0.0, "expectancy": 0.0, "sharpe_ratio": 0.0, "max_drawdown": 0.0, "total_pnl": 0.0, "avg_trade": 0.0, "liquidity_skips": 0, "price_skips": 0}}
